LICENSE
MANIFEST.in
README.rst
setup.cfg
setup.py
versioneer.py
artellapipe/__init__.py
artellapipe/libs/__init__.py
artellapipe/libs/kitsu/__init__.py
artellapipe/libs/kitsu/__logging__.ini
artellapipe/libs/kitsu/__version__.py
artellapipe/libs/kitsu/_version.py
artellapipe/libs/kitsu/core/__init__.py
artellapipe/libs/kitsu/core/kitsuclasses.py
artellapipe/libs/kitsu/core/kitsulib.py
artellapipe/libs/kitsu/core/tracking.py
artellapipe/libs/kitsu/resources/icons/color/kitsu.png
artellapipe/libs/kitsu/resources/icons/color/kitsu_off.png
artellapipe/libs/kitsu/resources/icons/color/kitsu_on.png
artellapipe/libs/kitsu/resources/icons/color/shutdown.png
artellapipe/libs/kitsu/resources/icons/default/kitsu.png
artellapipe/libs/kitsu/resources/icons/default/kitsu_off.png
artellapipe/libs/kitsu/resources/icons/default/kitsu_on.png
artellapipe/libs/kitsu/resources/icons/default/shutdown.png
artellapipe/libs/kitsu/resources/images/kitsu_no_login.png
artellapipe/libs/kitsu/widgets/__init__.py
artellapipe/libs/kitsu/widgets/logindialog.py
artellapipe/libs/kitsu/widgets/loginwidget.py
artellapipe/libs/kitsu/widgets/userinfo.py
artellapipe_libs_kitsu.egg-info/PKG-INFO
artellapipe_libs_kitsu.egg-info/SOURCES.txt
artellapipe_libs_kitsu.egg-info/dependency_links.txt
artellapipe_libs_kitsu.egg-info/not-zip-safe
artellapipe_libs_kitsu.egg-info/requires.txt
artellapipe_libs_kitsu.egg-info/top_level.txt
tests/__init__.py
tests/test_general.py