Metadata-Version: 2.1
Name: artellapipe-libs-kitsu
Version: 0.0.8
Summary: Library to handle Artella Project production tracking using Kitsu
Home-page: https://github.com/ArtellaPipe/artellapipe-libs-kitsu
Author: Tomas Poveda
Author-email: tpovedatd@gmail.com
License: MIT
Platform: UNKNOWN
Provides-Extra: test
Provides-Extra: dev
